datarush/__init__.py
datarush/__main__.py
datarush/config.py
datarush/exceptions.py
datarush/py.typed
datarush/run.py
datarush/version.py
datarush/core/__init__.py
datarush/core/dataflow.py
datarush/core/templates.py
datarush/core/types.py
datarush/core/operations/__init__.py
datarush/core/operations/sinks/__init__.py
datarush/core/operations/sinks/s3_dataset_sink.py
datarush/core/operations/sinks/s3_sink.py
datarush/core/operations/sources/__init__.py
datarush/core/operations/sources/local_file_source.py
datarush/core/operations/sources/s3_dataset_source.py
datarush/core/operations/sources/s3_object_source.py
datarush/core/operations/sources/send_http_request.py
datarush/core/operations/transformations/__init__.py
datarush/core/operations/transformations/add_range_column.py
datarush/core/operations/transformations/assert_has_columns.py
datarush/core/operations/transformations/astype.py
datarush/core/operations/transformations/calculate.py
datarush/core/operations/transformations/calculate_hash.py
datarush/core/operations/transformations/change_case.py
datarush/core/operations/transformations/columns_to_dict.py
datarush/core/operations/transformations/concatenate_tables.py
datarush/core/operations/transformations/copy_column.py
datarush/core/operations/transformations/copy_table.py
datarush/core/operations/transformations/deduplicate_column_values.py
datarush/core/operations/transformations/deduplicate_rows.py
datarush/core/operations/transformations/derive_column.py
datarush/core/operations/transformations/dict_to_columns.py
datarush/core/operations/transformations/dropna.py
datarush/core/operations/transformations/explode.py
datarush/core/operations/transformations/extract_regex_group.py
datarush/core/operations/transformations/fillna.py
datarush/core/operations/transformations/filter_row.py
datarush/core/operations/transformations/group_by.py
datarush/core/operations/transformations/join.py
datarush/core/operations/transformations/melt_table.py
datarush-0.10.0.dist-info/licenses/LICENSE
datarush-0.10.0.dist-info/METADATA
datarush-0.10.0.dist-info/WHEEL
datarush-0.10.0.dist-info/top_level.txt
datarush-0.10.0.dist-info/RECORD
