Metadata-Version: 2.4
Name: datarush
Version: 0.10.0
Summary: No-code data pipelines
Home-page: https://github.com/vadimtitov/datarush
Author: Vadim Titov
Author-email: titov.hse@gmail.com
Project-URL: Bug Tracker, https://github.com/vadimtitov/datarush/issues
Classifier: Development Status :: 3 - Alpha
Classifier: Intended Audience :: Developers
Classifier: License :: OSI Approved :: MIT License
Classifier: Operating System :: OS Independent
Classifier: Programming Language :: Python :: 3.11
Classifier: Programming Language :: Python :: 3.12
Classifier: Programming Language :: Python :: 3.13
Requires-Python: >=3.11
License-File: LICENSE
Requires-Dist: pydantic<3.0.0,>=2.10.6
Requires-Dist: pandas<3.0.0,>=2.2.3
Requires-Dist: streamlit<2.0.0,>=1.46.0
Requires-Dist: streamlit-ace<1.0.0,>=0.1.1
Requires-Dist: streamlit-modal<1.0.0,>=0.1.2
Requires-Dist: boto3<2.0.0,>=1.37.4
Requires-Dist: envarify<2.0.0,>=1.5.0
Requires-Dist: requests<3.0.0,>=2.32.3
Requires-Dist: python-dotenv<2.0.0,>=1.0.1
Requires-Dist: jinja2<4.0.0,>=3.1.5
Requires-Dist: awswrangler<4.0.0,>=3.11.0
Requires-Dist: dateparser<2.0.0,>=1.2.2
Provides-Extra: test
Requires-Dist: pytest; extra == "test"
Dynamic: license-file
